README.md
setup.py
Lsm_all_params_env/__init__.py
Lsm_all_params_env.egg-info/PKG-INFO
Lsm_all_params_env.egg-info/SOURCES.txt
Lsm_all_params_env.egg-info/dependency_links.txt
Lsm_all_params_env.egg-info/requires.txt
Lsm_all_params_env.egg-info/top_level.txt
Lsm_all_params_env/envs/__init__.py
Lsm_all_params_env/envs/all_params_env.py
Lsm_all_params_env/envs/curve_fit.py
Lsm_all_params_env/envs/exp_1_basic_2i3c.py
Lsm_all_params_env/envs/kinetic_modeling.py
Lsm_all_params_env/envs/module_for_exp.py
Lsm_all_params_env/envs/multiprocessing_env.py
Lsm_all_params_env/envs/opt_selfimple/__init__.py
Lsm_all_params_env/envs/opt_selfimple/deOpt.py
Lsm_all_params_env/envs/opt_selfimple/gaOpt.py
Lsm_all_params_env/envs/opt_selfimple/opt.py
Lsm_all_params_env/envs/opt_selfimple/pso.py
Lsm_all_params_env/envs/opt_selfimple/whaleOpt.py