Metadata-Version: 2.1
Name: Lsm-all-params-env
Version: 0.1
Summary: A openAI Gym Params-Env for lsm ALL_params
Home-page: UNKNOWN
License: UNKNOWN
Platform: UNKNOWN
